<?xml version="1.0" encoding="UTF-8"?>
<dataroot xmlns:od="urn:schemas-microsoft-com:officedata" xmlns:xsi="http://www.w3.org/2001/XMLSchema-instance"  xsi:noNamespaceSchemaLocation="refuge.xsd" generated="2012-06-18T17:27:32">
<refuge>
<no>1</no>
<typeno>1</typeno>
<type>徒歩</type>
<name>陽運寺</name>
<address>東京都新宿区左門町１８</address>
<latitude>35.6853904</latitude>
<longitude>139.7212464</longitude>
</refuge>
<refuge>
<no>2</no>
<typeno>1</typeno>
<type>徒歩</type>
<name>平河天満宮</name>
<address>東京都千代田区平河町１丁目７−５</address>
<latitude>35.6824339</latitude>
<longitude>139.7407651</longitude>
</refuge>
<refuge>
<no>3</no>
<typeno>1</typeno>
<type>徒歩</type>
<name>築地本願寺</name>
<address>東京都中央区築地３−１５−1</address>
<latitude>35.6665037</latitude>
<longitude>139.7721115</longitude>
</refuge>
<refuge>
<no>4</no>
<typeno>2</typeno>
<type>仕事運</type>
<name>代々木八幡宮</name>
<address>東京都渋谷区代々木５−１−１</address>
<latitude>35.6720917</latitude>
<longitude>139.6885757</longitude>
</refuge>
<refuge>
<no>5</no>
<typeno>2</typeno>
<type>仕事運</type>
<name>日枝神社</name>
<address>東京都千代田区永田町２丁目１０−５</address>
<latitude>35.6747103</latitude>
<longitude>139.7395557</longitude>
</refuge>
<refuge>
<no>6</no>
<typeno>2</typeno>
<type>仕事運</type>
<name>愛宕神社</name>
<address>東京都港区 愛宕1丁目5-3</address>
<latitude>35.6649171</latitude>
<longitude>139.748491</longitude>
</refuge>
<refuge>
<no>7</no>
<typeno>2</typeno>
<type>仕事運</type>
<name>神田明神</name>
<address>東京都千代田区外神田２−１６−２</address>
<latitude>35.702004</latitude>
<longitude>139.7679486</longitude>
</refuge>
<refuge>
<no>8</no>
<typeno>3</typeno>
<type>恋愛運</type>
<name>東京大神宮</name>
<address>東京都千代田区富士見２丁目４−１</address>
<latitude>35.6999727</latitude>
<longitude>139.7468079</longitude>
</refuge>
<refuge>
<no>9</no>
<typeno>3</typeno>
<type>恋愛運</type>
<name>神田明神</name>
<address>東京都千代田区外神田２−１６−２</address>
<latitude>35.702004</latitude>
<longitude>139.7679486</longitude>
</refuge>
<refuge>
<no>10</no>
<typeno>3</typeno>
<type>恋愛運</type>
<name>今戸神社</name>
<address>東京都台東区今戸１丁目５−２２</address>
<latitude>35.7193061</latitude>
<longitude>139.803541</longitude>
</refuge>
<refuge>
<no>11</no>
<typeno>4</typeno>
<type>健康運</type>
<name>芝大神宮</name>
<address>東京都港区芝大門１−１２−7</address>
<latitude>35.657596</latitude>
<longitude>139.7529324</longitude>
</refuge>
<refuge>
<no>12</no>
<typeno>4</typeno>
<type>健康運</type>
<name>稲荷鬼王神社</name>
<address>東京都新宿区歌舞伎町２丁目１７−５</address>
<latitude>35.697748</latitude>
<longitude>139.7053156</longitude>
</refuge>
<refuge>
<no>13</no>
<typeno>4</typeno>
<type>恋愛運</type>
<name>今戸神社</name>
<address>東京都台東区今戸１丁目５−２２</address>
<latitude>35.7193061</latitude>
<longitude>139.803541</longitude>
</refuge>
<refuge>
<no>14</no>
<typeno>4</typeno>
<type>健康運</type>
<name>日枝神社</name>
<address>東京都千代田区永田町２丁目１０−５</address>
<latitude>35.6747103</latitude>
<longitude>139.7395557</longitude>
</refuge>
</dataroot>